ApiKeyAJM/ApiKeyAJM.py
ApiKeyAJM/__init__.py
ApiKeyAJM/_version.py
apikeyajm-0.9.1.dist-info/licenses/LICENSE.txt
apikeyajm-0.9.1.dist-info/METADATA
apikeyajm-0.9.1.dist-info/WHEEL
apikeyajm-0.9.1.dist-info/top_level.txt
apikeyajm-0.9.1.dist-info/RECORD
