Metadata-Version: 2.4
Name: ApiKeyAJM
Version: 0.9.1
Summary: reusable API key getter
Home-page: https://github.com/amcsparron2793-Water/ApiKeyAJM
Download-URL: https://github.com/amcsparron2793-Water/ApiKeyAJM/archive/refs/tags/0.9.1.tar.gz
Author: Amcsparron
Author-email: amcsparron@albanyny.gov
License: MIT License
License-File: LICENSE.txt
Dynamic: author
Dynamic: author-email
Dynamic: download-url
Dynamic: home-page
Dynamic: license
Dynamic: license-file
Dynamic: summary
